simpy/io/__init__.py
simpy/io/_compat.py
simpy/io/access.py
simpy/io/async.py
simpy/io/asyncio.py
simpy/io/base.py
simpy/io/broker.py
simpy/io/codec.py
simpy/io/dispatcher.py
simpy/io/http.py
simpy/io/json.py
simpy/io/message.py
simpy/io/network.py
simpy/io/packet.py
simpy/io/platform.py
simpy/io/poll.py
simpy/io/select.py
simpy/io/virtual.py
simpy/io/websocket.py
simpy/io/test/__init__.py
simpy/io/test/broker.py
simpy/io/test/cacert.pem
simpy/io/test/conftest.py
simpy/io/test/http.py
simpy/io/test/json.py
simpy/io/test/message.py
simpy/io/test/packet.py
simpy/io/test/server.key
simpy/io/test/socket.py
simpy/io/test/test_access.py
simpy/io/test/test_codec.py
simpy/io/test/websocket.py
simpy/io/test/async/__init__.py
simpy/io/test/async/ssl/__init__.py
simpy/io/test/async/ssl/conftest.py
simpy/io/test/async/ssl/test_broker.py
simpy/io/test/async/ssl/test_http.py
simpy/io/test/async/ssl/test_json.py
simpy/io/test/async/ssl/test_message.py
simpy/io/test/async/ssl/test_packet.py
simpy/io/test/async/ssl/test_socket.py
simpy/io/test/async/ssl/test_websocket.py
simpy/io/test/async/tcp/__init__.py
simpy/io/test/async/tcp/conftest.py
simpy/io/test/async/tcp/test_broker.py
simpy/io/test/async/tcp/test_http.py
simpy/io/test/async/tcp/test_json.py
simpy/io/test/async/tcp/test_message.py
simpy/io/test/async/tcp/test_packet.py
simpy/io/test/async/tcp/test_socket.py
simpy/io/test/async/tcp/test_websocket.py
simpy/io/test/epoll/__init__.py
simpy/io/test/epoll/ssl/__init__.py
simpy/io/test/epoll/ssl/conftest.py
simpy/io/test/epoll/ssl/test_broker.py
simpy/io/test/epoll/ssl/test_http.py
simpy/io/test/epoll/ssl/test_json.py
simpy/io/test/epoll/ssl/test_message.py
simpy/io/test/epoll/ssl/test_packet.py
simpy/io/test/epoll/ssl/test_socket.py
simpy/io/test/epoll/ssl/test_websocket.py
simpy/io/test/epoll/tcp/__init__.py
simpy/io/test/epoll/tcp/conftest.py
simpy/io/test/epoll/tcp/test_broker.py
simpy/io/test/epoll/tcp/test_http.py
simpy/io/test/epoll/tcp/test_json.py
mosaik_simpy_io-0.2.4.dist-info/AUTHORS.txt
mosaik_simpy_io-0.2.4.dist-info/LICENSE.txt
mosaik_simpy_io-0.2.4.dist-info/METADATA
mosaik_simpy_io-0.2.4.dist-info/WHEEL
mosaik_simpy_io-0.2.4.dist-info/top_level.txt
mosaik_simpy_io-0.2.4.dist-info/RECORD
