Metadata-Version: 2.1
Name: mosaik-simpy-io
Version: 0.2.4
Summary: Asynchronous networking based on SimPy.
Home-page: https://gitlab.com/mosaik/tools/simpy.io
Author: mosaik
Author-email: mosaik@offis.de
License: MIT License
Platform: UNKNOWN
Classifier: Development Status :: 3 - Alpha
Classifier: Environment :: Console
Classifier: Intended Audience :: Developers
Classifier: Intended Audience :: Education
Classifier: Intended Audience :: Science/Research
Classifier: License :: OSI Approved :: MIT License
Classifier: Natural Language :: English
Classifier: Operating System :: OS Independent
Classifier: Programming Language :: Python
Classifier: Programming Language :: Python :: 3.5
Classifier: Programming Language :: Python :: 3.6
Classifier: Programming Language :: Python :: 3.7
Classifier: Programming Language :: Python :: 3.8
Classifier: Programming Language :: Python :: 3.9
Classifier: Topic :: Scientific/Engineering
Classifier: Topic :: System :: Networking
License-File: LICENSE.txt
License-File: AUTHORS.txt
